MANIFEST.in
README
setup.cfg
setup.py
common/__init__.py
common/cache.py
common/context_processors.py
common/decorators.py
common/enum.py
common/fields.py
common/forms.py
common/html.py
common/http.py
common/image.py
common/mail.py
common/middleware.py
common/orm.py
common/pagination.py
common/profile.py
common/progress.py
common/sample.py
common/system.py
common/thumbnail.py
common/data/app_template/__init__.py
common/data/app_template/admin.py
common/data/app_template/models.py
common/data/app_template/urls.py
common/data/app_template/views.py
common/locale/ru/LC_MESSAGES/django.mo
common/locale/ru/LC_MESSAGES/django.po
common/management/__init__.py
common/management/commands/__init__.py
common/management/commands/common_startapp.py
common/templates/pagination.html
common/templatetags/__init__.py
common/templatetags/common_tags.py
django_common.egg-info/PKG-INFO
django_common.egg-info/SOURCES.txt
django_common.egg-info/dependency_links.txt
django_common.egg-info/top_level.txt