Metadata-Version: 1.0
Name: django-common
Version: 0.1.49
Summary: A number of useful django shortcuts and helpers
Home-page: http://bitbucket.org/lorien/django-common/
Author: Grigoriy Petukhov
Author-email: lorien@lorien.name
License: BSD
Keywords: django application development shortcuts helpers
Platform: UNKNOWN
Classifier: Development Status :: 4 - Beta
Classifier: Environment :: Web Environment
Classifier: Framework :: Django
Classifier: Intended Audience :: Developers
Classifier: License :: OSI Approved :: BSD License
Classifier: Operating System :: OS Independent
Classifier: Programming Language :: Python
Classifier: Topic :: Software Development :: Libraries :: Python Modules
